{
  "title": "Gemeinde Zeuthen",
  "general": {
    "widgetMarkdown": "",
    "widgetFahrradklimatest": {
      "title": "Fahrradklimatest",
      "chartHorizontal": {
        "data": [],
        "legend": []
      }
    },
    "widgetVerkehrsbelastung": {
      "chartRelativeVertical": {
        "data": [],
        "dataUnit": "none"
      }
    }
  },
  "traffic": {
    "widgetPentlersaldo": {
      "chartVertical": {
        "data": [],
        "dataUnit": "none"
      }
    },
    "widgetFahrzeuge": {
      "chartVertical": {
        "data": [],
        "dataUnit": "none"
      }
    },
    "widgetModalsplit": {
      "chartVertical": {
        "data": [],
        "dataUnit": "none"
      }
    },
    "widgetStrassennetz": {
      "chartRelativeVertical": {
        "data": [],
        "dataUnit": "none"
      }
    },
    "widgetUnfaelle": {
      "list": []
    }
  },
  "goals": {
    "widgetMarkdown": "",
    "widgetPeople": "",
    "widgetInvestitionen": {
      "table": [],
      "chartHorizontal": {
        "data": [],
        "legend": []
      }
    }
  }
}
